rocksnot/__init__.py
rocksnot/foliumrock.py
rocksnot/rocksnot.py
rocksnot-0.0.10.dist-info/LICENSE
rocksnot-0.0.10.dist-info/METADATA
rocksnot-0.0.10.dist-info/WHEEL
rocksnot-0.0.10.dist-info/dependency_links.txt
rocksnot-0.0.10.dist-info/top_level.txt
rocksnot-0.0.10.dist-info/RECORD
