Metadata-Version: 2.1
Name: rocksnot
Version: 0.0.10
Summary: python package
Home-page: https://github.com/rlape28/rocksnot
Author: Robby Lape
Author-email: robby.lape@gmail.com
License: MIT license
Keywords: rocksnot
Classifier: Development Status :: 2 - Pre-Alpha
Classifier: Intended Audience :: Developers
Classifier: License :: OSI Approved :: MIT License
Classifier: Natural Language :: English
Classifier: Programming Language :: Python :: 3
Classifier: Programming Language :: Python :: 3.7
Classifier: Programming Language :: Python :: 3.8
Classifier: Programming Language :: Python :: 3.9
Classifier: Programming Language :: Python :: 3.10
Requires-Python: >=3.7
License-File: LICENSE
Requires-Dist: folium
Requires-Dist: ipyleaflet
Requires-Dist: geopandas
Requires-Dist: httpx
